odoo/addons/contract_queue_job/README.rst
odoo/addons/contract_queue_job/__init__.py
odoo/addons/contract_queue_job/__manifest__.py
odoo/addons/contract_queue_job/i18n/contract_queue_job.pot
odoo/addons/contract_queue_job/models/__init__.py
odoo/addons/contract_queue_job/models/contract_contract.py
odoo/addons/contract_queue_job/models/contract_line.py
odoo/addons/contract_queue_job/readme/CONTRIBUTORS.rst
odoo/addons/contract_queue_job/readme/DESCRIPTION.rst
odoo/addons/contract_queue_job/static/description/icon.png
odoo/addons/contract_queue_job/static/description/index.html
odoo/addons/contract_queue_job/tests/__init__.py
odoo/addons/contract_queue_job/tests/test_contract_line_queue_job.py
odoo/addons/contract_queue_job/tests/test_contract_queue_job.py
odoo/addons/contract_queue_job/wizards/__init__.py
odoo/addons/contract_queue_job/wizards/contract_manually_create_invoice.py
odoo12_addon_contract_queue_job-12.0.1.1.0.dist-info/METADATA
odoo12_addon_contract_queue_job-12.0.1.1.0.dist-info/WHEEL
odoo12_addon_contract_queue_job-12.0.1.1.0.dist-info/top_level.txt
odoo12_addon_contract_queue_job-12.0.1.1.0.dist-info/RECORD
